sw_product_lib/__init__.py
sw_product_lib/service.py
sw_product_lib/apps/__init__.py
sw_product_lib/apps/context.py
sw_product_lib/apps/middleware.py
sw_product_lib/apps/admin/__init__.py
sw_product_lib/apps/admin/backend.py
sw_product_lib/apps/admin/status.py
sw_product_lib/apps/auth/__init__.py
sw_product_lib/apps/auth/gcp.py
sw_product_lib/apps/auth/sw_proxy.py
sw_product_lib/apps/jobs/__init__.py
sw_product_lib/apps/jobs/_decorators/status.py
sw_product_lib/apps/jobs/_decorators/submitter.py
sw_product_lib/apps/jobs/types/__init__.py
sw_product_lib/apps/jobs/types/_artifact.py
sw_product_lib/apps/jobs/types/_base.py
sw_product_lib/client/__init__.py
sw_product_lib/client/backend.py
sw_product_lib/client/billing.py
sw_product_lib/client/job.py
sw_product_lib/client/resource.py
sw_product_lib/platform/__init__.py
sw_product_lib/platform/gql.py
sw_product_lib/types/__init__.py
sw_product_lib/types/backend.py
sw_product_lib/types/batch_job.py
sw_product_lib/types/job.py
sw_product_lib/types/resource.py
sw_product_lib/utils/__init__.py
sw_product_lib/utils/jwt_utils.py
sw_product_lib-0.10.4.dist-info/METADATA
sw_product_lib-0.10.4.dist-info/WHEEL
sw_product_lib-0.10.4.dist-info/RECORD
