Metadata-Version: 2.4
Name: sw-product-lib
Version: 0.10.4
Summary: Python library for Strangeworks products to interact with the Strangeworks Platform
Author-email: Strangeworks Devs <hello@strangeworks.com>
License-Expression: Apache-2.0
Requires-Python: <4,>=3.11
Requires-Dist: deprecated<2,>=1.2.13
Requires-Dist: fastapi<0.116,>=0.115.0
Requires-Dist: google-auth<3,>=2.29.0
Requires-Dist: gql<4,>=3.4.1
Requires-Dist: python-jose[cryptography]<4,>=3.3.0
Requires-Dist: strangeworks-core>=0.5.4
